{"_path":"/sample/s001","_dir":"sample","_draft":false,"_partial":false,"_locale":"","title":"社區照顧 C據點活動","description":"社區照顧 C據點活動 - 社區關懷中心 定期活動通告","image":null,"sequence":1001,"category1":"3. 社團活動與急難救濟","category2":"3.1 舉辦社團活動","link":"https://www.facebook.com/profile.php?id=100064026103094","author":"長庚里","head":{"meta":[{"name":"keywords","content":""},{"name":"robots","content":""},{"name":"author","content":"林俊源"},{"name":"copyright","content":"© 2024 A7新林口-社區網站"},{"name":"og:title","content":"地方行政"}]},"publishedAt":"2023-07-17T00:00:00.000Z","toc":true,"body":{"type":"root","children":[{"type":"element","tag":"p","props":{},"children":[{"type":"element","tag":"img","props":{"alt":"s001-01.jpeg","src":"/images/x.jpeg"},"children":[]}]}],"toc":{"title":"","searchDepth":2,"depth":2,"links":[]}},"_type":"markdown","_id":"content:sample:s001.md","_source":"content","_file":"sample/s001.md","_extension":"md"}